morning/.__init__.py.un~
morning/__init__.py
morning/morning.py
morning-0.1.5.dist-info/entry_points.txt
morning-0.1.5.dist-info/METADATA
morning-0.1.5.dist-info/WHEEL
morning-0.1.5.dist-info/RECORD
