Metadata-Version: 1.2
Name: morning
Version: 0.1.5
Summary: A simple module to do repetitive tasks in the morning. 
Home-page: https://github.com/Carreau/morning
License: UNKNOWN
Author: Matthias Bussonnier
Author-email: bussonniermatthias@gmail.com
